{
  "en": {
    "already_deleted": "has already been deleted.",
    "attached_instance": "Associated Instance",
    "attributes": "Attributes",
    "capacity_type": "Capacity ",
    "detach_volume_tip": "Before clicking the detach button, please stop read/write the volume and unmount it in your instance.",
    "performance_type": "Performance ",
    "read_only": "Read-Only",
    "read_write": "Read-Write",
    "server_infor_reqesting": "Instance info is requesting, please wait.",
    "shared": "Shared",
    "size": "Size"
  },
  "zh-CN": {
    "already_deleted": "已被删除",
    "attached_instance": "挂载的云主机",
    "attributes": "属性",
    "capacity_type": "容量型",
    "detach_volume_tip": "请先在虚拟机中对云硬盘停止读写并取消挂载，然后再点击卸载。",
    "performance_type": "性能型",
    "read_only": "只读盘",
    "read_write": "读写盘",
    "server_infor_reqesting": "云主机信息正在获取，请稍后。",
    "shared": "共享盘",
    "size": "容量"
  }
}